marimo_dev/__init__.py
marimo_dev/build.py
marimo_dev/cli.py
marimo_dev/core.py
marimo_dev/docs.py
marimo_dev/pkg.py
marimo_dev/publish.py
marimo_dev/read.py
marimo_dev-0.2.8.dist-info/WHEEL
marimo_dev-0.2.8.dist-info/entry_points.txt
marimo_dev-0.2.8.dist-info/METADATA
marimo_dev-0.2.8.dist-info/RECORD
