Metadata-Version: 2.3
Name: marimo-dev
Version: 0.2.8
Summary: Build and publish python packages from marimo notebooks
Author: Deufel
Author-email: Deufel <MDeufel13@gmail.com>
License: MIT
Requires-Dist: fastcore>=1.10.0
Requires-Dist: ipython>=9.8.0
Requires-Dist: marimo>=0.19.7
Requires-Dist: mohtml>=0.1.11
Requires-Dist: pydantic-ai-slim>=1.50.0
Requires-Dist: pytest>=9.0.2
Requires-Dist: python-fasthtml>=0.12.37
Requires-Dist: youtube-transcript-api>=1.2.3
Requires-Python: >=3.12
Project-URL: Repository, https://github.com/deufel/m-dev
Project-URL: PyPI, https://pypi.org/project/marimo-dev/
